pytopomojo/__init__.py
pytopomojo/pytopomojo.py
pytopomojo/examples/create-workspace.py
pytopomojo/examples/download-all-workspaces.py
pytopomojo/examples/upload-workspace.py
pytopomojo-0.1.6.dist-info/licenses/LICENSE
pytopomojo-0.1.6.dist-info/METADATA
pytopomojo-0.1.6.dist-info/WHEEL
pytopomojo-0.1.6.dist-info/top_level.txt
pytopomojo-0.1.6.dist-info/RECORD
