Metadata-Version: 2.4
Name: pytopomojo
Version: 0.1.6
Summary: Python wrapper for TopoMojo API
Author: Jarrett Booz
License: MIT
Requires-Python: >=3.8
License-File: LICENSE
Requires-Dist: requests>=2.25
Dynamic: license-file
